Workbook

Sheet Assumptions
A1: TERM ASSURANCE PRICING AND PROFIT TESTING MODEL
A3: Assumption | B3: Value
A4: Entry Age | B4: 30
A5: Policy Term (years) | B5: 20
A6: Sum Assured (₹) | B6: 10000000
A7: Premium Frequency | B7: Annual
A8: Mortality Basis | B8: IALM 2012-14 Ultimate
A9: Market 10Y G-Sec Yield | B9: 0.0711
A10: Pricing Interest Rate | B10: 0.065
A11: Mortality Loading | B11: 0.1
A12: Acquisition Expense (₹) | B12: 500
A13: Renewal Expense (₹) | B13: 150
A14: Variable Expense (% Premium) | B14: 0.05
A15: First-Year Commission (% Premium) | B15: 0.2
A16: Renewal Commission (% Premium) | B16: 0.05
A17: Target Profit Margin | B17: 0.1

Sheet Mortality
A1: Age | B1: qx | C1: Mortality Loading | D1: Pricing qx | E1: Source
A2: 30 | B2: 0.000977 | C2: =Assumptions!$B$11 -> 0.1 | D2: =B2*(1+C2) -> 0.0010747 | E2: =Assumptions!$B$8 -> IALM 2012-14 Ultimate
A3: 31 | B3: 0.001005 | C3: =Assumptions!$B$11 -> 0.1 | D3: =B3*(1+C3) -> 0.0011055 | E3: =Assumptions!$B$8 -> IALM 2012-14 Ultimate
A4: 32 | B4: 0.001042 | C4: =Assumptions!$B$11 -> 0.1 | D4: =B4*(1+C4) -> 0.0011462 | E4: =Assumptions!$B$8 -> IALM 2012-14 Ultimate
A5: 33 | B5: 0.001086 | C5: =Assumptions!$B$11 -> 0.1 | D5: =B5*(1+C5) -> 0.0011946 | E5: =Assumptions!$B$8 -> IALM 2012-14 Ultimate
A6: 34 | B6: 0.00114 | C6: =Assumptions!$B$11 -> 0.1 | D6: =B6*(1+C6) -> 0.001254 | E6: =Assumptions!$B$8 -> IALM 2012-14 Ultimate
A7: 35 | B7: 0.001202 | C7: =Assumptions!$B$11 -> 0.1 | D7: =B7*(1+C7) -> 0.0013222 | E7: =Assumptions!$B$8 -> IALM 2012-14 Ultimate
A8: 36 | B8: 0.001275 | C8: =Assumptions!$B$11 -> 0.1 | D8: =B8*(1+C8) -> 0.0014025 | E8: =Assumptions!$B$8 -> IALM 2012-14 Ultimate
A9: 37 | B9: 0.001358 | C9: =Assumptions!$B$11 -> 0.1 | D9: =B9*(1+C9) -> 0.0014938 | E9: =Assumptions!$B$8 -> IALM 2012-14 Ultimate
A10: 38 | B10: 0.001453 | C10: =Assumptions!$B$11 -> 0.1 | D10: =B10*(1+C10) -> 0.0015983 | E10: =Assumptions!$B$8 -> IALM 2012-14 Ultimate
A11: 39 | B11: 0.00156 | C11: =Assumptions!$B$11 -> 0.1 | D11: =B11*(1+C11) -> 0.001716 | E11: =Assumptions!$B$8 -> IALM 2012-14 Ultimate
A12: 40 | B12: 0.00168 | C12: =Assumptions!$B$11 -> 0.1 | D12: =B12*(1+C12) -> 0.001848 | E12: =Assumptions!$B$8 -> IALM 2012-14 Ultimate
A13: 41 | B13: 0.001815 | C13: =Assumptions!$B$11 -> 0.1 | D13: =B13*(1+C13) -> 0.0019965 | E13: =Assumptions!$B$8 -> IALM 2012-14 Ultimate
... A32: 60 | B32: 0.011162 | C32: =Assumptions!$B$11 -> 0.1 | D32: =B32*(1+C32) -> 0.0122782 | E32: =Assumptions!$B$8 -> IALM 2012-14 Ultimate

Sheet Expected Claims
A1: TERM ASSURANCE PREMIUM CALCULATION
A3: Policy Year | B3: Age | C3: Pricing qx | D3: Survival probability to year start | E3: Death Probability | F3: Discount factor | G3: PV of Expected Death Benefit
A4: 1 | B4: =Mortality!A2 -> 30 | C4: =Mortality!D2 -> 0.0010747 | D4: 1 | E4: =D4*C4 -> 0.0010747 | F4: =(1+Assumptions!$B$10)^-'Expected Claims'!A4 -> 0.93896714 | G4: =F4*E4*Assumptions!$B$6 -> 10091.08
A5: 2 | B5: =Mortality!A3 -> 31 | C5: =Mortality!D3 -> 0.0011055 | D5: =D4*(1-C4) -> 0.9989253 | E5: =D5*C5 -> 0.0011043119 | F5: =(1+Assumptions!$B$10)^-'Expected Claims'!A5 -> 0.88165928 | G5: =F5*E5*Assumptions!$B$6 -> 9736.2685
A6: 3 | B6: =Mortality!A4 -> 32 | C6: =Mortality!D4 -> 0.0011462 | D6: =D5*(1-C5) -> 0.99782099 | E6: =D6*C6 -> 0.0011437024 | F6: =(1+Assumptions!$B$10)^-'Expected Claims'!A6 -> 0.82784909 | G6: =F6*E6*Assumptions!$B$6 -> 9468.1301
A7: 4 | B7: =Mortality!A5 -> 33 | C7: =Mortality!D5 -> 0.0011946 | D7: =D6*(1-C6) -> 0.99667729 | E7: =D7*C7 -> 0.0011906307 | F7: =(1+Assumptions!$B$10)^-'Expected Claims'!A7 -> 0.77732309 | G7: =F7*E7*Assumptions!$B$6 -> 9255.0472
A8: 5 | B8: =Mortality!A6 -> 34 | C8: =Mortality!D6 -> 0.001254 | D8: =D7*(1-C7) -> 0.99548665 | E8: =D8*C8 -> 0.0012483403 | F8: =(1+Assumptions!$B$10)^-'Expected Claims'!A8 -> 0.72988084 | G8: =F8*E8*Assumptions!$B$6 -> 9111.3964
A9: 6 | B9: =Mortality!A7 -> 35 | C9: =Mortality!D7 -> 0.0013222 | D9: =D8*(1-C8) -> 0.99423831 | E9: =D9*C9 -> 0.0013145819 | F9: =(1+Assumptions!$B$10)^-'Expected Claims'!A9 -> 0.68533412 | G9: =F9*E9*Assumptions!$B$6 -> 9009.2783
A10: 7 | B10: =Mortality!A8 -> 36 | C10: =Mortality!D8 -> 0.0014025 | D10: =D9*(1-C9) -> 0.99292373 | E10: =D10*C10 -> 0.0013925755 | F10: =(1+Assumptions!$B$10)^-'Expected Claims'!A10 -> 0.64350621 | G10: =F10*E10*Assumptions!$B$6 -> 8961.3101
A11: 8 | B11: =Mortality!A9 -> 37 | C11: =Mortality!D9 -> 0.0014938 | D11: =D10*(1-C10) -> 0.99153116 | E11: =D11*C11 -> 0.0014811492 | F11: =(1+Assumptions!$B$10)^-'Expected Claims'!A11 -> 0.60423119 | G11: =F11*E11*Assumptions!$B$6 -> 8949.5657
A12: 9 | B12: =Mortality!A10 -> 38 | C12: =Mortality!D10 -> 0.0015983 | D12: =D11*(1-C11) -> 0.99005001 | E12: =D12*C12 -> 0.0015823969 | F12: =(1+Assumptions!$B$10)^-'Expected Claims'!A12 -> 0.56735323 | G12: =F12*E12*Assumptions!$B$6 -> 8977.78
A13: 10 | B13: =Mortality!A11 -> 39 | C13: =Mortality!D11 -> 0.001716 | D13: =D12*(1-C12) -> 0.98846761 | E13: =D13*C13 -> 0.0016962104 | F13: =(1+Assumptions!$B$10)^-'Expected Claims'!A13 -> 0.53272604 | G13: =F13*E13*Assumptions!$B$6 -> 9036.1545
A14: 11 | B14: =Mortality!A12 -> 40 | C14: =Mortality!D12 -> 0.001848 | D14: =D13*(1-C13) -> 0.9867714 | E14: =D14*C14 -> 0.0018235535 | F14: =(1+Assumptions!$B$10)^-'Expected Claims'!A14 -> 0.50021224 | G14: =F14*E14*Assumptions!$B$6 -> 9121.6381
A15: 12 | B15: =Mortality!A13 -> 41 | C15: =Mortality!D13 -> 0.0019965 | D15: =D14*(1-C14) -> 0.98494785 | E15: =D15*C15 -> 0.0019664484 | F15: =(1+Assumptions!$B$10)^-'Expected Claims'!A15 -> 0.46968285 | G15: =F15*E15*Assumptions!$B$6 -> 9236.0709
A16: 13 | B16: =Mortality!A14 -> 42 | C16: =Mortality!D14 -> 0.0021659 | D16: =D15*(1-C15) -> 0.9829814 | E16: =D16*C16 -> 0.0021290394 | F16: =(1+Assumptions!$B$10)^-'Expected Claims'!A16 -> 0.44101676 | G16: =F16*E16*Assumptions!$B$6 -> 9389.4207
... A23: 20 | B23: =Mortality!A21 -> 49 | C23: =Mortality!D21 -> 0.0043538 | D23: =D22*(1-C22) -> 0.96305247 | E23: =D23*C23 -> 0.0041929379 | F23: =(1+Assumptions!$B$10)^-'Expected Claims'!A23 -> 0.28379703 | G23: =F23*E23*Assumptions!$B$6 -> 11899.433
G25: =SUM(G4:G23) -> 194457.33

Sheet Premium Calculation
A1: TERM ASSURANCE PREMIUM CALCULATION
A3: Policy year | B3: Age | C3: Survival Probability | D3: Discount Factor | E3: Acquisition Expense | F3: Renewal Expense | G3: Variable Expense (% Premium) | H3: First-Year Commission | I3: Renewal Commission | J3: Total Fixed Expense | K3: Premium-Linked Expense Rate | L3: EPV Factor of Premium | M3: EPV Factor of Premium linked expenses | N3: EPV of fixed expenses
A4: 1 | B4: =Mortality!A2 -> 30 | C4: ='Expected Claims'!D4 -> 1 | D4: =(1+Assumptions!$B$10)^-(A4-1) -> 1 | E4: =Assumptions!B12 -> 500 | F4: 0 | G4: =Assumptions!$B$14 -> 0.05 | H4: =Assumptions!$B$15 -> 0.2 | I4: 0 | J4: =E4+F4 -> 500 | K4: =G4+H4+I4 -> 0.25 | L4: =C4*D4 -> 1 | M4: =L4*K4 -> 0.25 | N4: =J4*C4*D4 -> 500
A5: 2 | B5: =Mortality!A3 -> 31 | C5: ='Expected Claims'!D5 -> 0.9989253 | D5: =(1+Assumptions!$B$10)^-(A5-1) -> 0.93896714 | E5: 0 | F5: =Assumptions!$B$13 -> 150 | G5: =Assumptions!$B$14 -> 0.05 | H5: 0 | I5: =Assumptions!$B$16 -> 0.05 | J5: =E5+F5 -> 150 | K5: =G5+H5+I5 -> 0.1 | L5: =C5*D5 -> 0.93795803 | M5: =L5*K5 -> 0.093795803 | N5: =J5*C5*D5 -> 140.6937
A6: 3 | B6: =Mortality!A4 -> 32 | C6: ='Expected Claims'!D6 -> 0.99782099 | D6: =(1+Assumptions!$B$10)^-(A6-1) -> 0.88165928 | E6: 0 | F6: =Assumptions!$B$13 -> 150 | G6: =Assumptions!$B$14 -> 0.05 | H6: 0 | I6: =Assumptions!$B$16 -> 0.05 | J6: =E6+F6 -> 150 | K6: =G6+H6+I6 -> 0.1 | L6: =C6*D6 -> 0.87973814 | M6: =L6*K6 -> 0.087973814 | N6: =J6*C6*D6 -> 131.96072
A7: 4 | B7: =Mortality!A5 -> 33 | C7: ='Expected Claims'!D7 -> 0.99667729 | D7: =(1+Assumptions!$B$10)^-(A7-1) -> 0.82784909 | E7: 0 | F7: =Assumptions!$B$13 -> 150 | G7: =Assumptions!$B$14 -> 0.05 | H7: 0 | I7: =Assumptions!$B$16 -> 0.05 | J7: =E7+F7 -> 150 | K7: =G7+H7+I7 -> 0.1 | L7: =C7*D7 -> 0.82509839 | M7: =L7*K7 -> 0.082509839 | N7: =J7*C7*D7 -> 123.76476
A8: 5 | B8: =Mortality!A6 -> 34 | C8: ='Expected Claims'!D8 -> 0.99548665 | D8: =(1+Assumptions!$B$10)^-(A8-1) -> 0.77732309 | E8: 0 | F8: =Assumptions!$B$13 -> 150 | G8: =Assumptions!$B$14 -> 0.05 | H8: 0 | I8: =Assumptions!$B$16 -> 0.05 | J8: =E8+F8 -> 150 | K8: =G8+H8+I8 -> 0.1 | L8: =C8*D8 -> 0.77381476 | M8: =L8*K8 -> 0.077381476 | N8: =J8*C8*D8 -> 116.07221
A9: 6 | B9: =Mortality!A7 -> 35 | C9: ='Expected Claims'!D9 -> 0.99423831 | D9: =(1+Assumptions!$B$10)^-(A9-1) -> 0.72988084 | E9: 0 | F9: =Assumptions!$B$13 -> 150 | G9: =Assumptions!$B$14 -> 0.05 | H9: 0 | I9: =Assumptions!$B$16 -> 0.05 | J9: =E9+F9 -> 150 | K9: =G9+H9+I9 -> 0.1 | L9: =C9*D9 -> 0.72567549 | M9: =L9*K9 -> 0.072567549 | N9: =J9*C9*D9 -> 108.85132
A10: 7 | B10: =Mortality!A8 -> 36 | C10: ='Expected Claims'!D10 -> 0.99292373 | D10: =(1+Assumptions!$B$10)^-(A10-1) -> 0.68533412 | E10: 0 | F10: =Assumptions!$B$13 -> 150 | G10: =Assumptions!$B$14 -> 0.05 | H10: 0 | I10: =Assumptions!$B$16 -> 0.05 | J10: =E10+F10 -> 150 | K10: =G10+H10+I10 -> 0.1 | L10: =C10*D10 -> 0.68048451 | M10: =L10*K10 -> 0.068048451 | N10: =J10*C10*D10 -> 102.07268
A11: 8 | B11: =Mortality!A9 -> 37 | C11: ='Expected Claims'!D11 -> 0.99153116 | D11: =(1+Assumptions!$B$10)^-(A11-1) -> 0.64350621 | E11: 0 | F11: =Assumptions!$B$13 -> 150 | G11: =Assumptions!$B$14 -> 0.05 | H11: 0 | I11: =Assumptions!$B$16 -> 0.05 | J11: =E11+F11 -> 150 | K11: =G11+H11+I11 -> 0.1 | L11: =C11*D11 -> 0.63805646 | M11: =L11*K11 -> 0.063805646 | N11: =J11*C11*D11 -> 95.708469
A12: 9 | B12: =Mortality!A10 -> 38 | C12: ='Expected Claims'!D12 -> 0.99005001 | D12: =(1+Assumptions!$B$10)^-(A12-1) -> 0.60423119 | E12: 0 | F12: =Assumptions!$B$13 -> 150 | G12: =Assumptions!$B$14 -> 0.05 | H12: 0 | I12: =Assumptions!$B$16 -> 0.05 | J12: =E12+F12 -> 150 | K12: =G12+H12+I12 -> 0.1 | L12: =C12*D12 -> 0.59821909 | M12: =L12*K12 -> 0.059821909 | N12: =J12*C12*D12 -> 89.732864
A13: 10 | B13: =Mortality!A11 -> 39 | C13: ='Expected Claims'!D13 -> 0.98846761 | D13: =(1+Assumptions!$B$10)^-(A13-1) -> 0.56735323 | E13: 0 | F13: =Assumptions!$B$13 -> 150 | G13: =Assumptions!$B$14 -> 0.05 | H13: 0 | I13: =Assumptions!$B$16 -> 0.05 | J13: =E13+F13 -> 150 | K13: =G13+H13+I13 -> 0.1 | L13: =C13*D13 -> 0.56081029 | M13: =L13*K13 -> 0.056081029 | N13: =J13*C13*D13 -> 84.121543
A14: 11 | B14: =Mortality!A12 -> 40 | C14: ='Expected Claims'!D14 -> 0.9867714 | D14: =(1+Assumptions!$B$10)^-(A14-1) -> 0.53272604 | E14: 0 | F14: =Assumptions!$B$13 -> 150 | G14: =Assumptions!$B$14 -> 0.05 | H14: 0 | I14: =Assumptions!$B$16 -> 0.05 | J14: =E14+F14 -> 150 | K14: =G14+H14+I14 -> 0.1 | L14: =C14*D14 -> 0.52567882 | M14: =L14*K14 -> 0.052567882 | N14: =J14*C14*D14 -> 78.851822
A15: 12 | B15: =Mortality!A13 -> 41 | C15: ='Expected Claims'!D15 -> 0.98494785 | D15: =(1+Assumptions!$B$10)^-(A15-1) -> 0.50021224 | E15: 0 | F15: =Assumptions!$B$13 -> 150 | G15: =Assumptions!$B$14 -> 0.05 | H15: 0 | I15: =Assumptions!$B$16 -> 0.05 | J15: =E15+F15 -> 150 | K15: =G15+H15+I15 -> 0.1 | L15: =C15*D15 -> 0.49268297 | M15: =L15*K15 -> 0.049268297 | N15: =J15*C15*D15 -> 73.902445
A16: 13 | B16: =Mortality!A14 -> 42 | C16: ='Expected Claims'!D16 -> 0.9829814 | D16: =(1+Assumptions!$B$10)^-(A16-1) -> 0.46968285 | E16: 0 | F16: =Assumptions!$B$13 -> 150 | G16: =Assumptions!$B$14 -> 0.05 | H16: 0 | I16: =Assumptions!$B$16 -> 0.05 | J16: =E16+F16 -> 150 | K16: =G16+H16+I16 -> 0.1 | L16: =C16*D16 -> 0.46168951 | M16: =L16*K16 -> 0.046168951 | N16: =J16*C16*D16 -> 69.253426
... A23: 20 | B23: =Mortality!A21 -> 49 | C23: ='Expected Claims'!D23 -> 0.96305247 | D23: =(1+Assumptions!$B$10)^-(A23-1) -> 0.30224384 | E23: 0 | F23: =Assumptions!$B$13 -> 150 | G23: =Assumptions!$B$14 -> 0.05 | H23: 0 | I23: =Assumptions!$B$16 -> 0.05 | J23: =E23+F23 -> 150 | K23: =G23+H23+I23 -> 0.1 | L23: =C23*D23 -> 0.29107667 | M23: =L23*K23 -> 0.029107667 | N23: =J23*C23*D23 -> 43.661501
A25: EPV Factor of Annual Premiums | L25: =SUM(L4:L23) -> 11.607399
A26: EPV Factor of Premium-Linked Expenses | M26: =SUM(M4:M23) -> 1.3107399
A27: EPV of Fixed Expenses | N27: =SUM(N4:N23) -> 2091.1098
A29: EPV of Death Benefits | B29: ='Expected Claims'!G25 -> 194457.33
A30: EPV of Fixed Expenses | B30: =N27 -> 2091.1098
A31: EPV Factor of Annual Premiums | B31: =L25 -> 11.607399
A32: EPV Factor of Premium-Linked Expenses | B32: =M26 -> 1.3107399
A33: Total Profit Margin | B33: =Assumptions!$B$17 -> 0.1
A34: Annual Gross Premium | B34: =(B29+B30)/(B31-B32-(B31*B33)) -> 21513.811

Sheet Profit Testing
A1: TERM ASSURANCE PROFIT TESTING
A3: Policy Year | B3: Age | C3: Survival Probability | D3: Premium | E3: Death Probability | F3: Expected Death Benefit | G3: Acquisition Expense | H3: Renewal Expense | I3: Variable Expense | J3: First-Year Commission | K3: Renewal Commission | L3: Total Expenses | M3: Investment Income | N3: Profit | O3: Discount Factor | P3: Present Value of Profit
A4: 1 | B4: =Mortality!A2 -> 30 | C4: ='Expected Claims'!D4 -> 1 | D4: 21513.811 | E4: ='Expected Claims'!E4 -> 0.0010747 | F4: =E4*Assumptions!$B$6 -> 10747 | G4: ='Premium Calculation'!E4 -> 500 | H4: ='Premium Calculation'!F4 -> 0 | I4: =D4*'Premium Calculation'!G4 -> 1075.6906 | J4: =D4*'Premium Calculation'!H4 -> 4302.7623 | K4: =D4*'Premium Calculation'!I4 -> 0 | L4: =SUM(G4:K4) -> 5878.4528 | M4: =(D4-L4)*Assumptions!$B$10 -> 1016.2983 | N4: =D4+M4-L4-F4 -> 5904.6568 | O4: =(1+Assumptions!$B$10)^-'Profit Testing'!A4 -> 0.93896714 | P4: =N4*O4 -> 5544.2787
A5: 2 | B5: =Mortality!A3 -> 31 | C5: ='Expected Claims'!D5 -> 0.9989253 | D5: 21490.69 | E5: ='Expected Claims'!E5 -> 0.0011043119 | F5: =E5*Assumptions!$B$6 -> 11043.119 | G5: ='Premium Calculation'!E5 -> 0 | H5: ='Premium Calculation'!F5 -> 150 | I5: =D5*'Premium Calculation'!G5 -> 1074.5345 | J5: =D5*'Premium Calculation'!H5 -> 0 | K5: =D5*'Premium Calculation'!I5 -> 1074.5345 | L5: =SUM(G5:K5) -> 2299.069 | M5: =(D5-L5)*Assumptions!$B$10 -> 1247.4554 | N5: =D5+M5-L5-F5 -> 9395.9576 | O5: =(1+Assumptions!$B$10)^-'Profit Testing'!A5 -> 0.88165928 | P5: =N5*O5 -> 8284.0333
A6: 3 | B6: =Mortality!A4 -> 32 | C6: ='Expected Claims'!D6 -> 0.99782099 | D6: 21466.933 | E6: ='Expected Claims'!E6 -> 0.0011437024 | F6: =E6*Assumptions!$B$6 -> 11437.024 | G6: ='Premium Calculation'!E6 -> 0 | H6: ='Premium Calculation'!F6 -> 150 | I6: =D6*'Premium Calculation'!G6 -> 1073.3466 | J6: =D6*'Premium Calculation'!H6 -> 0 | K6: =D6*'Premium Calculation'!I6 -> 1073.3466 | L6: =SUM(G6:K6) -> 2296.6933 | M6: =(D6-L6)*Assumptions!$B$10 -> 1246.0656 | N6: =D6+M6-L6-F6 -> 8979.2807 | O6: =(1+Assumptions!$B$10)^-'Profit Testing'!A6 -> 0.82784909 | P6: =N6*O6 -> 7433.4893
A7: 4 | B7: =Mortality!A5 -> 33 | C7: ='Expected Claims'!D7 -> 0.99667729 | D7: 21442.327 | E7: ='Expected Claims'!E7 -> 0.0011906307 | F7: =E7*Assumptions!$B$6 -> 11906.307 | G7: ='Premium Calculation'!E7 -> 0 | H7: ='Premium Calculation'!F7 -> 150 | I7: =D7*'Premium Calculation'!G7 -> 1072.1164 | J7: =D7*'Premium Calculation'!H7 -> 0 | K7: =D7*'Premium Calculation'!I7 -> 1072.1164 | L7: =SUM(G7:K7) -> 2294.2327 | M7: =(D7-L7)*Assumptions!$B$10 -> 1244.6261 | N7: =D7+M7-L7-F7 -> 8486.4137 | O7: =(1+Assumptions!$B$10)^-'Profit Testing'!A7 -> 0.77732309 | P7: =N7*O7 -> 6596.6853
A8: 5 | B8: =Mortality!A6 -> 34 | C8: ='Expected Claims'!D8 -> 0.99548665 | D8: 21416.712 | E8: ='Expected Claims'!E8 -> 0.0012483403 | F8: =E8*Assumptions!$B$6 -> 12483.403 | G8: ='Premium Calculation'!E8 -> 0 | H8: ='Premium Calculation'!F8 -> 150 | I8: =D8*'Premium Calculation'!G8 -> 1070.8356 | J8: =D8*'Premium Calculation'!H8 -> 0 | K8: =D8*'Premium Calculation'!I8 -> 1070.8356 | L8: =SUM(G8:K8) -> 2291.6712 | M8: =(D8-L8)*Assumptions!$B$10 -> 1243.1277 | N8: =D8+M8-L8-F8 -> 7884.7659 | O8: =(1+Assumptions!$B$10)^-'Profit Testing'!A8 -> 0.72988084 | P8: =N8*O8 -> 5754.9395
A9: 6 | B9: =Mortality!A7 -> 35 | C9: ='Expected Claims'!D9 -> 0.99423831 | D9: 21389.856 | E9: ='Expected Claims'!E9 -> 0.0013145819 | F9: =E9*Assumptions!$B$6 -> 13145.819 | G9: ='Premium Calculation'!E9 -> 0 | H9: ='Premium Calculation'!F9 -> 150 | I9: =D9*'Premium Calculation'!G9 -> 1069.4928 | J9: =D9*'Premium Calculation'!H9 -> 0 | K9: =D9*'Premium Calculation'!I9 -> 1069.4928 | L9: =SUM(G9:K9) -> 2288.9856 | M9: =(D9-L9)*Assumptions!$B$10 -> 1241.5566 | N9: =D9+M9-L9-F9 -> 7196.6076 | O9: =(1+Assumptions!$B$10)^-'Profit Testing'!A9 -> 0.68533412 | P9: =N9*O9 -> 4932.0807
A10: 7 | B10: =Mortality!A8 -> 36 | C10: ='Expected Claims'!D10 -> 0.99292373 | D10: 21361.574 | E10: ='Expected Claims'!E10 -> 0.0013925755 | F10: =E10*Assumptions!$B$6 -> 13925.755 | G10: ='Premium Calculation'!E10 -> 0 | H10: ='Premium Calculation'!F10 -> 150 | I10: =D10*'Premium Calculation'!G10 -> 1068.0787 | J10: =D10*'Premium Calculation'!H10 -> 0 | K10: =D10*'Premium Calculation'!I10 -> 1068.0787 | L10: =SUM(G10:K10) -> 2286.1574 | M10: =(D10-L10)*Assumptions!$B$10 -> 1239.9021 | N10: =D10+M10-L10-F10 -> 6389.5632 | O10: =(1+Assumptions!$B$10)^-'Profit Testing'!A10 -> 0.64350621 | P10: =N10*O10 -> 4111.7236
A11: 8 | B11: =Mortality!A9 -> 37 | C11: ='Expected Claims'!D11 -> 0.99153116 | D11: 21331.614 | E11: ='Expected Claims'!E11 -> 0.0014811492 | F11: =E11*Assumptions!$B$6 -> 14811.492 | G11: ='Premium Calculation'!E11 -> 0 | H11: ='Premium Calculation'!F11 -> 150 | I11: =D11*'Premium Calculation'!G11 -> 1066.5807 | J11: =D11*'Premium Calculation'!H11 -> 0 | K11: =D11*'Premium Calculation'!I11 -> 1066.5807 | L11: =SUM(G11:K11) -> 2283.1614 | M11: =(D11-L11)*Assumptions!$B$10 -> 1238.1494 | N11: =D11+M11-L11-F11 -> 5475.1099 | O11: =(1+Assumptions!$B$10)^-'Profit Testing'!A11 -> 0.60423119 | P11: =N11*O11 -> 3308.2321
A12: 9 | B12: =Mortality!A10 -> 38 | C12: ='Expected Claims'!D12 -> 0.99005001 | D12: 21299.749 | E12: ='Expected Claims'!E12 -> 0.0015823969 | F12: =E12*Assumptions!$B$6 -> 15823.969 | G12: ='Premium Calculation'!E12 -> 0 | H12: ='Premium Calculation'!F12 -> 150 | I12: =D12*'Premium Calculation'!G12 -> 1064.9875 | J12: =D12*'Premium Calculation'!H12 -> 0 | K12: =D12*'Premium Calculation'!I12 -> 1064.9875 | L12: =SUM(G12:K12) -> 2279.9749 | M12: =(D12-L12)*Assumptions!$B$10 -> 1236.2853 | N12: =D12+M12-L12-F12 -> 4432.0903 | O12: =(1+Assumptions!$B$10)^-'Profit Testing'!A12 -> 0.56735323 | P12: =N12*O12 -> 2514.5607
A13: 10 | B13: =Mortality!A11 -> 39 | C13: ='Expected Claims'!D13 -> 0.98846761 | D13: 21265.706 | E13: ='Expected Claims'!E13 -> 0.0016962104 | F13: =E13*Assumptions!$B$6 -> 16962.104 | G13: ='Premium Calculation'!E13 -> 0 | H13: ='Premium Calculation'!F13 -> 150 | I13: =D13*'Premium Calculation'!G13 -> 1063.2853 | J13: =D13*'Premium Calculation'!H13 -> 0 | K13: =D13*'Premium Calculation'!I13 -> 1063.2853 | L13: =SUM(G13:K13) -> 2276.5706 | M13: =(D13-L13)*Assumptions!$B$10 -> 1234.2938 | N13: =D13+M13-L13-F13 -> 3261.3247 | O13: =(1+Assumptions!$B$10)^-'Profit Testing'!A13 -> 0.53272604 | P13: =N13*O13 -> 1737.3926
A14: 11 | B14: =Mortality!A12 -> 40 | C14: ='Expected Claims'!D14 -> 0.9867714 | D14: 21229.214 | E14: ='Expected Claims'!E14 -> 0.0018235535 | F14: =E14*Assumptions!$B$6 -> 18235.535 | G14: ='Premium Calculation'!E14 -> 0 | H14: ='Premium Calculation'!F14 -> 150 | I14: =D14*'Premium Calculation'!G14 -> 1061.4607 | J14: =D14*'Premium Calculation'!H14 -> 0 | K14: =D14*'Premium Calculation'!I14 -> 1061.4607 | L14: =SUM(G14:K14) -> 2272.9214 | M14: =(D14-L14)*Assumptions!$B$10 -> 1232.159 | N14: =D14+M14-L14-F14 -> 1952.9159 | O14: =(1+Assumptions!$B$10)^-'Profit Testing'!A14 -> 0.50021224 | P14: =N14*O14 -> 976.87245
A15: 12 | B15: =Mortality!A13 -> 41 | C15: ='Expected Claims'!D15 -> 0.98494785 | D15: 21189.982 | E15: ='Expected Claims'!E15 -> 0.0019664484 | F15: =E15*Assumptions!$B$6 -> 19664.484 | G15: ='Premium Calculation'!E15 -> 0 | H15: ='Premium Calculation'!F15 -> 150 | I15: =D15*'Premium Calculation'!G15 -> 1059.4991 | J15: =D15*'Premium Calculation'!H15 -> 0 | K15: =D15*'Premium Calculation'!I15 -> 1059.4991 | L15: =SUM(G15:K15) -> 2268.9982 | M15: =(D15-L15)*Assumptions!$B$10 -> 1229.864 | N15: =D15+M15-L15-F15 -> 486.36417 | O15: =(1+Assumptions!$B$10)^-'Profit Testing'!A15 -> 0.46968285 | P15: =N15*O15 -> 228.43691
... A23: 20 | B23: =Mortality!A21 -> 49 | C23: ='Expected Claims'!D23 -> 0.96305247 | D23: 20718.929 | E23: ='Expected Claims'!E23 -> 0.0041929379 | F23: =E23*Assumptions!$B$6 -> 41929.379 | G23: ='Premium Calculation'!E23 -> 0 | H23: ='Premium Calculation'!F23 -> 150 | I23: =D23*'Premium Calculation'!G23 -> 1035.9465 | J23: =D23*'Premium Calculation'!H23 -> 0 | K23: =D23*'Premium Calculation'!I23 -> 1035.9465 | L23: =SUM(G23:K23) -> 2221.8929 | M23: =(D23-L23)*Assumptions!$B$10 -> 1202.3074 | N23: =D23+M23-L23-F23 -> -22230.035 | O23: =(1+Assumptions!$B$10)^-'Profit Testing'!A23 -> 0.28379703 | P23: =N23*O23 -> -6308.8179
A25: Total PV of Profit | P25: =SUM(P4:P23) -> 24952.842

Sheet Sensitivity Analysis
A1: TERM ASSURANCE SENSITIVITY ANALYSIS
A3: Scenario | B3: Change | C3: Annual Premium | D3: PV of Profit (Base Premium)
A4: Base Case | B4: No change | C4: 21513.811 | D4: 24952.842
A5: Interest rate + 1% | B5: 0.01 | C5: 20876.231 | D5: 28752.302
A6: Interest rate - 1% | B6: -0.01 | C6: 22187.162 | D6: 20180.828
A7: Mortality + 10% | B7: 0.1 | C7: 23439.567 | D7: 7572.4312
A8: Mortality - 10% | B8: -0.1 | C8: 19586.516 | D8: 42382.338
A9: Expenses + 10% | B9: 0.1 | C9: 21850.187 | D9: 21921.92
A10: Expenses - 10% | B10: -0.1 | C10: 21186.951 | D10: 27983.763

Sheet Summary Dashboard
A1: TERM ASSURANCE PRICING AND PROFIT TESTING MODEL
A3: PROJECT OVERVIEW
A4: Entry Age | B4: =Assumptions!B4 -> 30
A5: Policy Term | B5: =Assumptions!B5 -> 20
A6: Sum Assured | B6: =Assumptions!B6 -> 10000000
A7: =Assumptions!A7 -> Premium Frequency | B7: =Assumptions!B7 -> Annual
A8: =Assumptions!A8 -> Mortality Basis | B8: =Assumptions!B8 -> IALM 2012-14 Ultimate
A9: =Assumptions!A9 -> Market 10Y G-Sec Yield | B9: =Assumptions!B9 -> 0.0711
A10: =Assumptions!A10 -> Pricing Interest Rate | B10: =Assumptions!B10 -> 0.065
A11: =Assumptions!A11 -> Mortality Loading | B11: =Assumptions!B11 -> 0.1
A12: Target Profit Margin | B12: 0.1
A14: KEY RESULTS
A15: Annual Premium | B15: ='Premium Calculation'!B34 -> 21513.811
A16: EPV of Premiums | B16: ='Premium Calculation'!B31*'Premium Calculation'!B34 -> 249719.38
A17: EPV of Claims | B17: ='Expected Claims'!G25 -> 194457.33
A18: EPV of Expenses | B18: ='Premium Calculation'!B30+('Premium Calculation'!B32*'Premium Calculation'!B34) -> 30290.12
A19: Present Value of Profit | B19: ='Profit Testing'!P25 -> 24952.842
A21: SENSITIVITY ANALYSIS
A22: Scenario | B22: PV of Profit
A23: ='Sensitivity Analysis'!A6 -> Interest rate - 1% | B23: ='Sensitivity Analysis'!D6 -> 20180.828
A24: ='Sensitivity Analysis'!A4 -> Base Case | B24: =B19 -> 24952.842
A25: ='Sensitivity Analysis'!A5 -> Interest rate + 1% | B25: ='Sensitivity Analysis'!D5 -> 28752.302
A26: ='Sensitivity Analysis'!A8 -> Mortality - 10% | B26: ='Sensitivity Analysis'!D8 -> 42382.338
A27: ='Sensitivity Analysis'!A7 -> Mortality + 10% | B27: ='Sensitivity Analysis'!D7 -> 7572.4312
A28: ='Sensitivity Analysis'!A10 -> Expenses - 10% | B28: ='Sensitivity Analysis'!D10 -> 27983.763
A29: ='Sensitivity Analysis'!A9 -> Expenses + 10% | B29: ='Sensitivity Analysis'!D9 -> 21921.92
A31: KEY OBSERVATIONS
A32: Higer mortality increases expected claims and reduces the present value of profit.
A33: Higher expenses increase the present value of expenses and reduce the present value of profit.
A34: Higher interest rate reduces the present value of future cash flows, while ower interest rate increases it.
A35: Sensitivity analysis demonstates how changes in key assumptions affect the profitability of the policy.
